efficientmetrics/__init__.py
efficientmetrics/metrics.py
efficientmetrics-0.1.0.dist-info/LICENSE
efficientmetrics-0.1.0.dist-info/METADATA
efficientmetrics-0.1.0.dist-info/WHEEL
efficientmetrics-0.1.0.dist-info/top_level.txt
efficientmetrics-0.1.0.dist-info/RECORD
