Metadata-Version: 2.1
Name: efficientmetrics
Version: 0.1.0
Summary: A package for efficient calculation of classification metrics.
Home-page: https://github.com/HuzeyfeAyaz/efficientmetrics
Author: Huzeyfe Ayaz
Author-email: huzeyfeayaz23@gmail.com
Classifier: Programming Language :: Python :: 3
Classifier: License :: OSI Approved :: MIT License
Classifier: Operating System :: OS Independent
Requires-Python: >=3.6
License-File: LICENSE
Requires-Dist: numpy >=1.19.2
